a_cv2_find_biggest_square/LICENSE
a_cv2_find_biggest_square/README.MD
a_cv2_find_biggest_square/__init__.py
a_cv2_find_biggest_square/requirements.txt
a_cv2_find_biggest_square/thirdparty.json
a_cv2_find_biggest_square-0.10.dist-info/LICENSE.rst
a_cv2_find_biggest_square-0.10.dist-info/METADATA
a_cv2_find_biggest_square-0.10.dist-info/WHEEL
a_cv2_find_biggest_square-0.10.dist-info/top_level.txt
a_cv2_find_biggest_square-0.10.dist-info/RECORD
